odoo/addons/web_leaflet_draw_lib/README.rst
odoo/addons/web_leaflet_draw_lib/__init__.py
odoo/addons/web_leaflet_draw_lib/__manifest__.py
odoo/addons/web_leaflet_draw_lib/i18n/it.po
odoo/addons/web_leaflet_draw_lib/i18n/web_leaflet_draw_lib.pot
odoo/addons/web_leaflet_draw_lib/readme/CONTRIBUTORS.md
odoo/addons/web_leaflet_draw_lib/readme/CREDITS.md
odoo/addons/web_leaflet_draw_lib/readme/DESCRIPTION.md
odoo/addons/web_leaflet_draw_lib/static/description/icon.png
odoo/addons/web_leaflet_draw_lib/static/description/index.html
odoo/addons/web_leaflet_draw_lib/static/lib/leaflet.draw/leaflet.draw.css
odoo/addons/web_leaflet_draw_lib/static/lib/leaflet.draw/leaflet.draw.js
odoo/addons/web_leaflet_draw_lib/static/lib/leaflet.draw/images/spritesheet-2x.png
odoo/addons/web_leaflet_draw_lib/static/lib/leaflet.draw/images/spritesheet.svg
odoo_addon_web_leaflet_draw_lib-18.0.1.0.0.3.dist-info/METADATA
odoo_addon_web_leaflet_draw_lib-18.0.1.0.0.3.dist-info/WHEEL
odoo_addon_web_leaflet_draw_lib-18.0.1.0.0.3.dist-info/top_level.txt
odoo_addon_web_leaflet_draw_lib-18.0.1.0.0.3.dist-info/RECORD
