Metadata-Version: 2.1
Name: odoo-addon-web_leaflet_draw_lib
Version: 18.0.1.0.0.3
Requires-Python: >=3.10
Requires-Dist: odoo-addon-web_leaflet_lib==18.0.*
Requires-Dist: odoo==18.0.*
Summary: Bring leaflet.draw.js library in odoo.
Home-page: https://github.com/OCA/geospatial
License: AGPL-3
Author: Advance Insight, Odoo Community Association (OCA)
Author-email: support@odoo-community.org
Classifier: Programming Language :: Python
Classifier: Framework :: Odoo
Classifier: Framework :: Odoo :: 18.0
Classifier: License :: OSI Approved :: GNU Affero General Public License v3
